bohicalog/__init__.py
bohicalog/__main__.py
bohicalog/colors.py
bohicalog/jsonformat.py
bohicalog/py.typed
bohicalog/utils.py
bohicalog/version.py
bohicalog/cli/__init__.py
bohicalog/cli/cli.py
bohicalog/cli/handlers/__init__.py
bohicalog/cli/handlers/telegram/__init__.py
bohicalog/cli/handlers/telegram/commands.py
bohicalog/handlers/__init__.py
bohicalog/handlers/telegram/__init__.py
bohicalog/handlers/telegram/buffer.py
bohicalog/handlers/telegram/consts.py
bohicalog/handlers/telegram/formatters.py
bohicalog/handlers/telegram/handler.py
bohicalog/handlers/telegram/utils.py
bohicalog-1.1.3.dist-info/LICENSE
bohicalog-1.1.3.dist-info/METADATA
bohicalog-1.1.3.dist-info/WHEEL
bohicalog-1.1.3.dist-info/entry_points.txt
bohicalog-1.1.3.dist-info/top_level.txt
bohicalog-1.1.3.dist-info/RECORD
