Metadata-Version: 2.1
Name: bohicalog
Version: 1.1.3
Summary: The BOHICA Logging Library provides a configured logger for you module or application
Home-page: https://github.com/BOHICA-Labs/bohicalog
Download-URL: https://github.com/BOHICA-Labs/bohicalog/releases
Author: Joshua Magady
Author-email: josh.magady@gmail.com
Maintainer: Joshua Magady
Maintainer-email: josh.magady@gmail.com
License: MIT
Project-URL: Bug Tracker, https://github.com/BOHICA-Labs/bohicalog/issues
Project-URL: Source Code, https://github.com/BOHICA-Labs/bohicalog
Keywords: snekpack,cookiecutter
Classifier: Development Status :: 1 - Planning
Classifier: Environment :: Console
Classifier: Intended Audience :: Developers
Classifier: License :: OSI Approved :: MIT License
Classifier: Operating System :: OS Independent
Classifier: Framework :: Pytest
Classifier: Framework :: tox
Classifier: Framework :: Sphinx
Classifier: Programming Language :: Python
Classifier: Programming Language :: Python :: 3.8
Classifier: Programming Language :: Python :: 3.9
Classifier: Programming Language :: Python :: 3.10
Classifier: Programming Language :: Python :: 3.11
Classifier: Programming Language :: Python :: 3 :: Only
Requires-Python: >=3.8
License-File: LICENSE
Requires-Dist: more-itertools (==9.0.0)
Requires-Dist: tqdm (==4.64.1)
Requires-Dist: requests (==2.28.1)
Requires-Dist: cloudscraper (==1.2.66)
Requires-Dist: retry (==0.9.2)
Requires-Dist: click (==8.1.3)
Requires-Dist: more-click (==0.1.2)
Requires-Dist: colorama (==0.4.4) ; sys_platform == "win32"
Provides-Extra: dev
Requires-Dist: pytest (==6.2.5) ; extra == 'dev'
Requires-Dist: coverage (==6.0) ; extra == 'dev'
Requires-Dist: python-dotenv (>=0.19.1) ; extra == 'dev'
Requires-Dist: sphinx (>=4.0.0) ; extra == 'dev'
Requires-Dist: furo (==2022.9.15) ; extra == 'dev'
Requires-Dist: sphinx-rtd-theme (>=0.5.2) ; extra == 'dev'
Requires-Dist: sphinx-click (>=2.5.0) ; extra == 'dev'
Requires-Dist: click-extra (>=3.6.0) ; extra == 'dev'
Requires-Dist: sphinxcontrib-programoutput (>=0.16) ; extra == 'dev'
Requires-Dist: sphinx-autodoc-typehints (>=1.12.0) ; extra == 'dev'
Requires-Dist: sphinx-automodapi (>=0.13) ; extra == 'dev'
Requires-Dist: pre-commit (>=2.15.0) ; extra == 'dev'
Requires-Dist: tox ; extra == 'dev'
Requires-Dist: bump2version (>=1.0.1) ; extra == 'dev'
Requires-Dist: twine (>=3.4.2) ; extra == 'dev'
Requires-Dist: wheel (>=0.36.2) ; extra == 'dev'
Provides-Extra: docs
Requires-Dist: python-dotenv (>=0.19.1) ; extra == 'docs'
Requires-Dist: sphinx (>=4.0.0) ; extra == 'docs'
Requires-Dist: furo (==2022.9.15) ; extra == 'docs'
Requires-Dist: pytest (==6.2.5) ; extra == 'docs'
Requires-Dist: sphinx-rtd-theme (>=0.5.2) ; extra == 'docs'
Requires-Dist: sphinx-click (>=2.5.0) ; extra == 'docs'
Requires-Dist: click-extra (>=3.6.0) ; extra == 'docs'
Requires-Dist: sphinxcontrib-programoutput (>=0.16) ; extra == 'docs'
Requires-Dist: sphinx-autodoc-typehints (>=1.12.0) ; extra == 'docs'
Requires-Dist: sphinx-automodapi (>=0.13) ; extra == 'docs'
Provides-Extra: tests
Requires-Dist: pytest (==6.2.5) ; extra == 'tests'
Requires-Dist: coverage (==6.0) ; extra == 'tests'
Requires-Dist: python-dotenv (>=0.19.1) ; extra == 'tests'
